[
  {
    "name": "Test Space 1",
    "city": "Bangkok",
    "category": "coworking",
    "address_string": "123 Test Street, Bangkok",
    "coordinates": {
      "latitude": 13.7524938,
      "longitude": 100.4935089
    },
    "description_short": "Updated description for test space 1",
    "digital_nomad_features": ["fast_wifi", "coffee"]
  },
  {
    "name": "Test Space 3",
    "city": "Chiang Mai",
    "category": "cafe",
    "address_string": "456 Test St, Chiang Mai",
    "coordinates": {
      "latitude": 18.7861,
      "longitude": 98.9847
    },
    "description_short": "A new test space in Chiang Mai",
    "digital_nomad_features": ["fast_wifi"]
  }
]
